{
    "libraries": {
        "event-handler": "git@github.com:grzegorz-grzeda/event-handler.git",
        "callbacks": "git@github.com:grzegorz-grzeda/callbacks.git",
        "uuid": "git@github.com:grzegorz-grzeda/uuid.git",
        "flow": "git@github.com:grzegorz-grzeda/flow.git",
        "cli": "git@github.com:grzegorz-grzeda/cli.git",
        "containers": "git@github.com:grzegorz-grzeda/containers.git",
        "color-manipulation": "git@github.com:grzegorz-grzeda/color-manipulation.git",
        "g2labs-log": "git@github.com:grzegorz-grzeda/g2labs-log.git",
        "atomic-tests": "git@github.com:grzegorz-grzeda/atomic-tests.git",
        "divulge": "git@github.com:grzegorz-grzeda/divulge.git",
        "encodings": "git@github.com:grzegorz-grzeda/encodings.git",
        "audit": "git@github.com:grzegorz-grzeda/audit.git",
        "stream-server": "git@github.com:grzegorz-grzeda/stream-server.git",
        "font": "git@github.com:grzegorz-grzeda/font.git",
        "generic-controller": "git@github.com:grzegorz-grzeda/generic-controller.git",
        "generic-display": "git@github.com:grzegorz-grzeda/generic-display.git",
        "ssd1306": "git@github.com:grzegorz-grzeda/ssd1306.git"
    }
}